tom_gemini_community/__init__.py
tom_gemini_community/gemini_gsselect.py
tom_gemini_community-0.3.2.dist-info/LICENSE
tom_gemini_community-0.3.2.dist-info/METADATA
tom_gemini_community-0.3.2.dist-info/WHEEL
tom_gemini_community-0.3.2.dist-info/top_level.txt
tom_gemini_community-0.3.2.dist-info/RECORD
