Metadata-Version: 2.1
Name: tom-gemini-community
Version: 0.3.2
Summary: Gemini Observatory Community TOM Broker Modules
Home-page: https://github.com/TOMToolkit/tom_gemini_community
Author: Bryan Miller
Author-email: millerwbryan@gmail.com
License: UNKNOWN
Keywords: tomtoolkit,astronomy,astrophysics,cosmology,science,fits,observatory,gemini
Platform: UNKNOWN
Classifier: Intended Audience :: Science/Research
Classifier: License :: OSI Approved :: GNU General Public License v3 (GPLv3)
Classifier: Operating System :: OS Independent
Classifier: Programming Language :: Python :: 3
Classifier: Programming Language :: Python :: 3.6
Classifier: Topic :: Scientific/Engineering :: Astronomy
Classifier: Topic :: Scientific/Engineering :: Physics
License-File: LICENSE
Requires-Dist: tomtoolkit
Requires-Dist: gsselect
